salamencrypt/__init__.py
salamencrypt/salamencrypt.py
salamencrypt-1.0.2.dist-info/LICENSE
salamencrypt-1.0.2.dist-info/METADATA
salamencrypt-1.0.2.dist-info/WHEEL
salamencrypt-1.0.2.dist-info/top_level.txt
salamencrypt-1.0.2.dist-info/RECORD
