Metadata-Version: 2.1
Name: salamencrypt
Version: 1.0.2
Summary: • Encrypt & Run Code Tool Python .
Home-page: https://t.me/T5B55
Author: salammzere3
Author-email: salamhunter@gmail.com
Project-URL: Bug Tracker, https://github.com/pypa/sampleproject/issues
Classifier: Programming Language :: Python :: 3
Classifier: Programming Language :: Python :: 2
Classifier: License :: OSI Approved :: MIT License
Classifier: Operating System :: OS Independent
Requires-Python: >=3
License-File: LICENSE
